dbd_py.py
dbd_py-0.2.8.dist-info/WHEEL
dbd_py-0.2.8.dist-info/METADATA
dbd_py-0.2.8.dist-info/RECORD
