Metadata-Version: 2.1
Name: dbd-py
Version: 0.2.8
Summary: Cool Discord Bot Designer module for python by Edited Cocktail
License: Alpachi License 2.0
Author: Edited Cockatail
Requires-Python: >=3.6,<4.0
Classifier: License :: Other/Proprietary License
Classifier: Programming Language :: Python :: 3
Classifier: Programming Language :: Python :: 3.6
Classifier: Programming Language :: Python :: 3.7
Classifier: Programming Language :: Python :: 3.8
Classifier: Programming Language :: Python :: 3.9
